[
  {
    "_id": "5f6154fdd835ea81f0933459",
    "index": 0,
    "guid": "f80622e8-d4c5-481e-83a2-9cc2c1eea6b4",
    "isActive": false,
    "balance": "$3,048.11",
    "picture": "http://placehold.it/32x32",
    "age": 27,
    "eyeColor": "blue",
    "name": "Jenifer Avila",
    "gender": "female",
    "company": "MARKETOID",
    "email": "jeniferavila@marketoid.com",
    "phone": "+1 (928) 426-2344",
    "address": "656 Ocean Parkway, Staples, Missouri, 4314",
    "about": "Veniam tempor reprehenderit et officia. Labore nisi cillum quis voluptate qui nostrud sint voluptate. Sit cupidatat commodo eu ullamco occaecat incididunt ea Lorem nulla commodo pariatur et.\r\n",
    "registered": "2014-04-28T09:25:09 +05:00",
    "latitude": 9.570971,
    "longitude": -48.476788,
    "tags": [
      "excepteur",
      "culpa",
      "incididunt",
      "cillum",
      "eiusmod",
      "consequat",
      "in"
    ],
    "friends": [
      {
        "id": 0,
        "name": "Gwendolyn Willis"
      },
      {
        "id": 1,
        "name": "Diaz Moreno"
      },
      {
        "id": 2,
        "name": "Carolina Neal"
      }
    ],
    "greeting": "Hello, Jenifer Avila! You have 9 unread messages.",
    "favoriteFruit": "banana"
  },
  {
    "_id": "5f6154fd1b098b58d9dc1568",
    "index": 1,
    "guid": "832877b4-ed80-4c1d-9dcb-cfeb7387af1a",
    "isActive": true,
    "balance": "$3,841.61",
    "picture": "http://placehold.it/32x32",
    "age": 37,
    "eyeColor": "blue",
    "name": "Dale Parks",
    "gender": "male",
    "company": "ZENTILITY",
    "email": "daleparks@zentility.com",
    "phone": "+1 (986) 558-3689",
    "address": "924 Carlton Avenue, Yonah, Alaska, 7858",
    "about": "Deserunt dolor veniam aute dolore velit. Officia fugiat ex exercitation culpa duis est amet est elit. Est consectetur velit sit exercitation duis esse ullamco reprehenderit consequat pariatur amet commodo nisi eu. Incididunt esse exercitation culpa ipsum aute anim nostrud elit. Elit sint labore culpa nostrud sunt non.\r\n",
    "registered": "2015-06-28T07:33:52 +05:00",
    "latitude": 67.797151,
    "longitude": 64.280679,
    "tags": [
      "aliqua",
      "voluptate",
      "cupidatat",
      "aliquip",
      "duis",
      "minim",
      "est"
    ],
    "friends": [
      {
        "id": 0,
        "name": "Forbes Sharpe"
      },
      {
        "id": 1,
        "name": "Strickland Kim"
      },
      {
        "id": 2,
        "name": "Robinson Sharp"
      }
    ],
    "greeting": "Hello, Dale Parks! You have 6 unread messages.",
    "favoriteFruit": "banana"
  },
  {
    "_id": "5f6154fd8e65df6f01f36b77",
    "index": 2,
    "guid": "21c194ab-9c29-4f71-a4da-06d365c535cc",
    "isActive": false,
    "balance": "$2,898.45",
    "picture": "http://placehold.it/32x32",
    "age": 29,
    "eyeColor": "brown",
    "name": "Kirkland Mccarty",
    "gender": "male",
    "company": "IDEGO",
    "email": "kirklandmccarty@idego.com",
    "phone": "+1 (836) 517-2013",
    "address": "285 Hegeman Avenue, Gibbsville, North Dakota, 667",
    "about": "In exercitation velit sunt ad velit laborum commodo do laborum id adipisicing incididunt. Cillum tempor aliquip nostrud consequat laboris pariatur nisi id anim nisi. Id sint do ut cillum exercitation id nulla reprehenderit reprehenderit duis in fugiat cupidatat officia. Deserunt adipisicing dolor proident minim adipisicing eu magna velit amet labore proident.\r\n",
    "registered": "2020-05-08T01:22:10 +05:00",
    "latitude": 59.407696,
    "longitude": -160.783114,
    "tags": [
      "adipisicing",
      "culpa",
      "dolor",
      "aute",
      "anim",
      "nostrud",
      "proident"
    ],
    "friends": [
      {
        "id": 0,
        "name": "Inez Madden"
      },
      {
        "id": 1,
        "name": "Suzanne Atkinson"
      },
      {
        "id": 2,
        "name": "Lavonne Wyatt"
      }
    ],
    "greeting": "Hello, Kirkland Mccarty! You have 3 unread messages.",
    "favoriteFruit": "apple"
  },
  {
    "_id": "5f6154fd089b3c6dd178021d",
    "index": 3,
    "guid": "8e3e52fd-ada4-49be-9b0d-26ca029ccd20",
    "isActive": true,
    "balance": "$2,501.76",
    "picture": "http://placehold.it/32x32",
    "age": 31,
    "eyeColor": "blue",
    "name": "Beard Mann",
    "gender": "male",
    "company": "NEOCENT",
    "email": "beardmann@neocent.com",
    "phone": "+1 (821) 498-3782",
    "address": "835 Stryker Court, Richmond, Arkansas, 2813",
    "about": "Ea id in veniam quis nisi id labore ea occaecat adipisicing Lorem. Dolor anim ad elit pariatur labore deserunt est non consectetur. Laborum dolor et aliquip fugiat do officia proident ea fugiat eu nostrud voluptate. Qui minim ipsum aute deserunt labore cupidatat sit exercitation. Consectetur eu voluptate et aliquip sunt pariatur. Cillum quis labore laborum aliquip quis id ullamco quis voluptate sunt aliquip nisi eu officia.\r\n",
    "registered": "2017-02-02T03:00:02 +05:00",
    "latitude": -89.442417,
    "longitude": -173.81296,
    "tags": [
      "nisi",
      "consequat",
      "commodo",
      "adipisicing",
      "exercitation",
      "nisi",
      "adipisicing"
    ],
    "friends": [
      {
        "id": 0,
        "name": "Patti Nelson"
      },
      {
        "id": 1,
        "name": "Brewer Delacruz"
      },
      {
        "id": 2,
        "name": "Alexis Vincent"
      }
    ],
    "greeting": "Hello, Beard Mann! You have 5 unread messages.",
    "favoriteFruit": "strawberry"
  },
  {
    "_id": "5f6154fd0d27de57f18d5a0f",
    "index": 4,
    "guid": "540da30b-b5a7-4e3a-9469-bb0a3ade2446",
    "isActive": false,
    "balance": "$1,802.67",
    "picture": "http://placehold.it/32x32",
    "age": 22,
    "eyeColor": "blue",
    "name": "Mary Johns",
    "gender": "female",
    "company": "ZILLACON",
    "email": "maryjohns@zillacon.com",
    "phone": "+1 (946) 463-3385",
    "address": "224 Catherine Street, Basye, Ohio, 3455",
    "about": "Ad eiusmod nisi Lorem qui excepteur irure Lorem ad. Officia dolor culpa culpa mollit. Dolore exercitation sit voluptate voluptate.\r\n",
    "registered": "2016-03-28T12:47:40 +05:00",
    "latitude": -32.02148,
    "longitude": -153.294797,
    "tags": [
      "tempor",
      "dolor",
      "voluptate",
      "laboris",
      "do",
      "pariatur",
      "irure"
    ],
    "friends": [
      {
        "id": 0,
        "name": "Lucinda Cobb"
      },
      {
        "id": 1,
        "name": "Vera Cortez"
      },
      {
        "id": 2,
        "name": "Sonia Arnold"
      }
    ],
    "greeting": "Hello, Mary Johns! You have 5 unread messages.",
    "favoriteFruit": "apple"
  },
  {
    "_id": "5f6154fec28d4549235d5b12",
    "index": 5,
    "guid": "eb92dd7a-a892-4b8a-a27a-e9bcb7634fa6",
    "isActive": false,
    "balance": "$2,868.81",
    "picture": "http://placehold.it/32x32",
    "age": 23,
    "eyeColor": "blue",
    "name": "Estelle Roach",
    "gender": "female",
    "company": "ZENCO",
    "email": "estelleroach@zenco.com",
    "phone": "+1 (989) 416-2389",
    "address": "587 Pine Street, Herlong, District Of Columbia, 8095",
    "about": "Cillum occaecat elit sit cupidatat cupidatat et aute dolor non enim laborum esse veniam aliqua. Irure excepteur qui incididunt excepteur dolor et nulla sint deserunt laboris qui. Consequat nisi eu dolor cupidatat eiusmod cillum cupidatat. Laboris laboris sint laborum magna consectetur ullamco id tempor incididunt adipisicing est.\r\n",
    "registered": "2017-04-09T07:10:05 +05:00",
    "latitude": 44.747706,
    "longitude": -31.490711,
    "tags": [
      "exercitation",
      "officia",
      "labore",
      "pariatur",
      "excepteur",
      "culpa",
      "commodo"
    ],
    "friends": [
      {
        "id": 0,
        "name": "Aimee Valentine"
      },
      {
        "id": 1,
        "name": "Cooley Bonner"
      },
      {
        "id": 2,
        "name": "Kate Mccoy"
      }
    ],
    "greeting": "Hello, Estelle Roach! You have 4 unread messages.",
    "favoriteFruit": "banana"
  },
  {
    "_id": "5f6154fe592d865410bb5273",
    "index": 6,
    "guid": "12178c5f-3640-4665-ab10-2808d4f70476",
    "isActive": true,
    "balance": "$1,010.38",
    "picture": "http://placehold.it/32x32",
    "age": 22,
    "eyeColor": "brown",
    "name": "Lessie Rollins",
    "gender": "female",
    "company": "GEOLOGIX",
    "email": "lessierollins@geologix.com",
    "phone": "+1 (899) 481-2018",
    "address": "302 Anchorage Place, Englevale, Marshall Islands, 3378",
    "about": "Commodo ex excepteur nostrud do nostrud esse mollit sunt ex. Veniam aliquip cupidatat veniam et officia et reprehenderit aute nulla sint laborum exercitation dolore qui. Dolore sint irure velit officia.\r\n",
    "registered": "2014-12-08T12:41:23 +05:00",
    "latitude": 82.920281,
    "longitude": 17.941294,
    "tags": [
      "irure",
      "ipsum",
      "est",
      "est",
      "ex",
      "elit",
      "Lorem"
    ],
    "friends": [
      {
        "id": 0,
        "name": "Frederick Cook"
      },
      {
        "id": 1,
        "name": "Manning Greer"
      },
      {
        "id": 2,
        "name": "Guerrero Gilbert"
      }
    ],
    "greeting": "Hello, Lessie Rollins! You have 2 unread messages.",
    "favoriteFruit": "banana"
  },
  {
    "_id": "5f6154fe397bf4ef7f751ddf",
    "index": 7,
    "guid": "d13c0893-1e44-47b1-aead-d32291b84b7d",
    "isActive": true,
    "balance": "$2,710.40",
    "picture": "http://placehold.it/32x32",
    "age": 23,
    "eyeColor": "brown",
    "name": "Eleanor Levine",
    "gender": "female",
    "company": "ELPRO",
    "email": "eleanorlevine@elpro.com",
    "phone": "+1 (847) 467-2660",
    "address": "645 Billings Place, Shaft, Washington, 5997",
    "about": "Exercitation ut commodo sint reprehenderit aliqua dolore consequat minim mollit ad aliquip et mollit nostrud. Eu cupidatat reprehenderit deserunt cupidatat proident consectetur consequat laboris aliquip. Occaecat est elit cillum do adipisicing adipisicing cupidatat ullamco velit commodo ea cupidatat.\r\n",
    "registered": "2015-06-10T07:04:36 +05:00",
    "latitude": 65.855212,
    "longitude": 136.076946,
    "tags": [
      "excepteur",
      "mollit",
      "tempor",
      "dolor",
      "dolor",
      "irure",
      "occaecat"
    ],
    "friends": [
      {
        "id": 0,
        "name": "Avis Kemp"
      },
      {
        "id": 1,
        "name": "Tracy Jacobs"
      },
      {
        "id": 2,
        "name": "Kristine Mcdowell"
      }
    ],
    "greeting": "Hello, Eleanor Levine! You have 6 unread messages.",
    "favoriteFruit": "apple"
  },
  {
    "_id": "5f6154feb13be79bdb42c22e",
    "index": 8,
    "guid": "7efd64f8-62bb-4e06-ba58-da73b09f5cbb",
    "isActive": true,
    "balance": "$1,652.84",
    "picture": "http://placehold.it/32x32",
    "age": 26,
    "eyeColor": "brown",
    "name": "Caldwell Dunlap",
    "gender": "male",
    "company": "ANIVET",
    "email": "caldwelldunlap@anivet.com",
    "phone": "+1 (906) 440-2126",
    "address": "994 Hinsdale Street, Sperryville, New Jersey, 2269",
    "about": "Sunt esse ullamco aliquip ipsum tempor minim voluptate ex. Lorem nostrud excepteur adipisicing sunt aliqua sunt. Laboris cupidatat irure proident eiusmod nisi aliqua. Qui dolore enim mollit ipsum Lorem pariatur excepteur non.\r\n",
    "registered": "2018-01-10T02:42:54 +05:00",
    "latitude": 72.899029,
    "longitude": 25.763633,
    "tags": [
      "amet",
      "nisi",
      "aliquip",
      "ea",
      "laboris",
      "nisi",
      "voluptate"
    ],
    "friends": [
      {
        "id": 0,
        "name": "Mollie Austin"
      },
      {
        "id": 1,
        "name": "Anna Adams"
      },
      {
        "id": 2,
        "name": "Jewel Craft"
      }
    ],
    "greeting": "Hello, Caldwell Dunlap! You have 1 unread messages.",
    "favoriteFruit": "banana"
  },
  {
    "_id": "5f6154fed26a294caf85db56",
    "index": 9,
    "guid": "6993264c-29e0-4375-be28-90ba1a698055",
    "isActive": true,
    "balance": "$3,304.54",
    "picture": "http://placehold.it/32x32",
    "age": 24,
    "eyeColor": "green",
    "name": "Knowles Maddox",
    "gender": "male",
    "company": "TRIPSCH",
    "email": "knowlesmaddox@tripsch.com",
    "phone": "+1 (908) 421-3090",
    "address": "518 Cooper Street, Stevens, Maine, 2907",
    "about": "Tempor consectetur mollit amet qui est velit nostrud enim deserunt sit dolore ad excepteur aliqua. Pariatur non dolor tempor exercitation anim. Ad voluptate culpa do deserunt laboris culpa ullamco exercitation. Id sunt irure fugiat Lorem cillum nulla exercitation labore elit exercitation esse quis ad.\r\n",
    "registered": "2020-04-11T12:26:54 +05:00",
    "latitude": 73.723346,
    "longitude": 4.899573,
    "tags": [
      "proident",
      "ipsum",
      "do",
      "quis",
      "mollit",
      "incididunt",
      "mollit"
    ],
    "friends": [
      {
        "id": 0,
        "name": "Taylor Copeland"
      },
      {
        "id": 1,
        "name": "Colleen Greene"
      },
      {
        "id": 2,
        "name": "Sallie Tillman"
      }
    ],
    "greeting": "Hello, Knowles Maddox! You have 7 unread messages.",
    "favoriteFruit": "apple"
  },
  {
    "_id": "5f6154fe2f16bbabd2d4bf5e",
    "index": 10,
    "guid": "3c683af7-097d-41c2-85ea-0836d9f2203b",
    "isActive": true,
    "balance": "$1,591.27",
    "picture": "http://placehold.it/32x32",
    "age": 36,
    "eyeColor": "blue",
    "name": "Briggs Welch",
    "gender": "male",
    "company": "SENMEI",
    "email": "briggswelch@senmei.com",
    "phone": "+1 (931) 476-3479",
    "address": "465 Grove Street, Trucksville, California, 1862",
    "about": "Dolore duis fugiat sint aliquip labore veniam enim ullamco laborum nostrud consectetur nostrud esse anim. Irure cupidatat ea et nisi proident ut nostrud Lorem deserunt nostrud culpa fugiat eu. Velit voluptate eiusmod et labore consequat sunt.\r\n",
    "registered": "2015-09-11T06:49:10 +05:00",
    "latitude": 87.915228,
    "longitude": 155.204107,
    "tags": [
      "in",
      "officia",
      "velit",
      "incididunt",
      "eiusmod",
      "sit",
      "id"
    ],
    "friends": [
      {
        "id": 0,
        "name": "Cassandra Cruz"
      },
      {
        "id": 1,
        "name": "Stephens Sanchez"
      },
      {
        "id": 2,
        "name": "Gallegos Pittman"
      }
    ],
    "greeting": "Hello, Briggs Welch! You have 7 unread messages.",
    "favoriteFruit": "strawberry"
  },
  {
    "_id": "5f6154fec7f26ba2e529922e",
    "index": 11,
    "guid": "0118defe-5a8b-4636-baf4-d361ee475409",
    "isActive": true,
    "balance": "$2,282.88",
    "picture": "http://placehold.it/32x32",
    "age": 24,
    "eyeColor": "brown",
    "name": "Audra Albert",
    "gender": "female",
    "company": "EARWAX",
    "email": "audraalbert@earwax.com",
    "phone": "+1 (898) 448-3810",
    "address": "572 Amboy Street, Calvary, American Samoa, 9931",
    "about": "Voluptate do nulla occaecat adipisicing non sunt eiusmod sint fugiat reprehenderit ex. Sit ullamco do aliquip aliqua officia et occaecat ipsum anim non cupidatat aliqua anim. Ad anim commodo sunt in eu laborum aute. In voluptate ad reprehenderit cupidatat sit ad reprehenderit elit minim officia laborum deserunt. Anim proident aliquip magna pariatur duis. Dolore pariatur mollit nulla nostrud ullamco in.\r\n",
    "registered": "2019-06-28T05:59:18 +05:00",
    "latitude": -24.678099,
    "longitude": -128.622585,
    "tags": [
      "aliqua",
      "do",
      "cillum",
      "minim",
      "dolor",
      "consequat",
      "excepteur"
    ],
    "friends": [
      {
        "id": 0,
        "name": "Perry Cameron"
      },
      {
        "id": 1,
        "name": "Rosario Bird"
      },
      {
        "id": 2,
        "name": "Sheppard Clements"
      }
    ],
    "greeting": "Hello, Audra Albert! You have 2 unread messages.",
    "favoriteFruit": "banana"
  },
  {
    "_id": "5f6154fef5cd08eda0f8a31a",
    "index": 12,
    "guid": "f14c37c5-1ccd-46f4-b14c-3d5236857f1c",
    "isActive": true,
    "balance": "$3,998.33",
    "picture": "http://placehold.it/32x32",
    "age": 34,
    "eyeColor": "blue",
    "name": "Nola Schmidt",
    "gender": "female",
    "company": "URBANSHEE",
    "email": "nolaschmidt@urbanshee.com",
    "phone": "+1 (946) 416-2324",
    "address": "685 Bancroft Place, Bluffview, Kentucky, 7590",
    "about": "Fugiat in sit labore qui aliquip ullamco laboris et nulla officia. Dolore est ullamco ex velit non ipsum sunt. Enim elit enim reprehenderit eu elit. Mollit minim labore incididunt consectetur dolor laboris reprehenderit qui. Adipisicing irure non cillum dolore sunt cupidatat enim aliquip culpa id quis velit adipisicing ea. Irure tempor exercitation culpa sint veniam aute.\r\n",
    "registered": "2019-07-25T09:59:45 +05:00",
    "latitude": -1.3317,
    "longitude": 140.717692,
    "tags": [
      "culpa",
      "eu",
      "laboris",
      "excepteur",
      "do",
      "officia",
      "ad"
    ],
    "friends": [
      {
        "id": 0,
        "name": "Sandoval Roberson"
      },
      {
        "id": 1,
        "name": "Camille Kirkland"
      },
      {
        "id": 2,
        "name": "Rosanne Horn"
      }
    ],
    "greeting": "Hello, Nola Schmidt! You have 9 unread messages.",
    "favoriteFruit": "banana"
  },
  {
    "_id": "5f6154fea481aaf64c4a40c6",
    "index": 13,
    "guid": "9e7766c4-e5aa-4d74-b393-be2287448cd0",
    "isActive": false,
    "balance": "$2,218.26",
    "picture": "http://placehold.it/32x32",
    "age": 22,
    "eyeColor": "green",
    "name": "Kristina Ramirez",
    "gender": "female",
    "company": "UBERLUX",
    "email": "kristinaramirez@uberlux.com",
    "phone": "+1 (822) 433-2864",
    "address": "844 Village Road, Day, New Mexico, 2035",
    "about": "Non Lorem pariatur magna in ex nulla est. Do ullamco magna fugiat consequat dolore qui sint minim fugiat. Dolore id deserunt tempor amet elit anim et.\r\n",
    "registered": "2015-12-08T11:23:15 +05:00",
    "latitude": 41.612118,
    "longitude": 178.625669,
    "tags": [
      "aliqua",
      "duis",
      "veniam",
      "aliquip",
      "consequat",
      "labore",
      "fugiat"
    ],
    "friends": [
      {
        "id": 0,
        "name": "Lee Daniels"
      },
      {
        "id": 1,
        "name": "Bridgett Nielsen"
      },
      {
        "id": 2,
        "name": "Bernadette Mcdaniel"
      }
    ],
    "greeting": "Hello, Kristina Ramirez! You have 1 unread messages.",
    "favoriteFruit": "apple"
  }
]